CHANGELOG.rst
LICENSE.txt
MANIFEST.in
README.rst
setup.py
fresco_genshi/__init__.py
fresco_genshi.egg-info/PKG-INFO
fresco_genshi.egg-info/SOURCES.txt
fresco_genshi.egg-info/dependency_links.txt
fresco_genshi.egg-info/not-zip-safe
fresco_genshi.egg-info/requires.txt
fresco_genshi.egg-info/top_level.txt